[
  { "id": "64bcf886", "name": "Grayson", "age": 36 },
  { "id": "69328ca7", "name": "Atwater", "age": 73 },
  { "id": "63c6e4b2", "name": "Alecia", "age": 54 },
  { "id": "39f8b262", "name": "Parris", "age": 42 },
  { "id": "f4e6b70e", "name": "Keithley", "age": 52 },
  { "id": "b4a7e052", "name": "Housum", "age": 24 },
  { "id": "d5f16b94", "name": "Dyane", "age": 20 },
  { "id": "e95b3a90", "name": "Loesceke", "age": 72 },
  { "id": "701a31b2", "name": "Wiebmer", "age": 36 },
  { "id": "510048f5", "name": "Johm", "age": 49 },
  { "id": "d3f016ad", "name": "Eddra", "age": 37 },
  { "id": "b1052113", "name": "Sielen", "age": 25 },
  { "id": "da39540c", "name": "Pirali", "age": 52 },
  { "id": "7e4394f0", "name": "Venn", "age": 72 },
  { "id": "e15834e2", "name": "Clapper", "age": 32 },
  { "id": "85401f16", "name": "Brietta", "age": 66 },
  { "id": "c4daf54", "name": "Katinka", "age": 84 },
  { "id": "ff494314", "name": "Bernt", "age": 26 },
  { "id": "5fb717cc", "name": "Beffrey", "age": 66 },
  { "id": "b68f958c", "name": "Sopher", "age": 30 },
  { "id": "a279c25e", "name": "Gala", "age": 72 },
  { "id": "6e3ccea1", "name": "Perry", "age": 83 },
  { "id": "670c0be0", "name": "Jase", "age": 26 },
  { "id": "b1315875", "name": "Hedveh", "age": 67 },
  { "id": "89e0aa66", "name": "Nodababus", "age": 74 },
  { "id": "75e1cd3", "name": "Steele", "age": 51 },
  { "id": "89ba8a6a", "name": "Davie", "age": 28 },
  { "id": "d57c6aa1", "name": "Crowell", "age": 75 },
  { "id": "e39cd6ec", "name": "Odilo", "age": 44 },
  { "id": "61fd34d2", "name": "Donela", "age": 78 },
  { "id": "d489f3ef", "name": "Alten", "age": 47 },
  { "id": "5b60773e", "name": "Evvie", "age": 74 },
  { "id": "62ffe536", "name": "Baras", "age": 82 },
  { "id": "52180ddd", "name": "Hui", "age": 41 },
  { "id": "3835fcf7", "name": "Amalburga", "age": 19 },
  { "id": "e531b26d", "name": "Winikka", "age": 51 },
  { "id": "928b9bbb", "name": "Lorne", "age": 43 },
  { "id": "bc21bcc4", "name": "Prosperus", "age": 56 },
  { "id": "d711fadc", "name": "Heimlich", "age": 78 },
  { "id": "74429642", "name": "Mortimer", "age": 34 },
  { "id": "ee96b1b1", "name": "River", "age": 53 },
  { "id": "f40e602b", "name": "Atkins", "age": 43 },
  { "id": "6e0e5f49", "name": "Rebe", "age": 33 },
  { "id": "8ae47fc5", "name": "Orban", "age": 41 },
  { "id": "200679b9", "name": "Jordison", "age": 85 },
  { "id": "a5e3d7d1", "name": "Oribelle", "age": 17 },
  { "id": "6c41f8d0", "name": "Wivinia", "age": 40 },
  { "id": "1cb7c1bd", "name": "Oly", "age": 69 },
  { "id": "9534cf09", "name": "Laforge", "age": 63 },
  { "id": "5b82c5be", "name": "Wivestad", "age": 64 },
  { "id": "9cd9d0d2", "name": "Margette", "age": 52 },
  { "id": "32196f7e", "name": "Leopold", "age": 28 },
  { "id": "fa6f7fd6", "name": "Kristina", "age": 48 },
  { "id": "52a4f20b", "name": "Loeb", "age": 75 },
  { "id": "aaef6be0", "name": "Calli", "age": 56 },
  { "id": "a2060993", "name": "Dedra", "age": 65 },
  { "id": "10420584", "name": "Durante", "age": 50 },
  { "id": "6b97b491", "name": "Sharleen", "age": 79 },
  { "id": "f6f188d0", "name": "Joletta", "age": 82 },
  { "id": "2108e8d2", "name": "Crockett", "age": 34 },
  { "id": "fcde4225", "name": "Charlean", "age": 33 },
  { "id": "a6a91ea9", "name": "Nisse", "age": 25 },
  { "id": "90967444", "name": "Cooke", "age": 54 },
  { "id": "390c12f3", "name": "Russo", "age": 41 },
  { "id": "f5ce63bc", "name": "Barger", "age": 74 },
  { "id": "7cdc9ad", "name": "Tita", "age": 17 },
  { "id": "d207f1ba", "name": "Vivian", "age": 60 },
  { "id": "bf2ad978", "name": "Hagar", "age": 26 },
  { "id": "fdcfec92", "name": "Ralston", "age": 58 },
  { "id": "96a199f3", "name": "Gad", "age": 83 },
  { "id": "e6d379f8", "name": "Fanchet", "age": 56 },
  { "id": "d34a2139", "name": "Nadiya", "age": 81 },
  { "id": "bc78059a", "name": "Virgel", "age": 58 },
  { "id": "d616918e", "name": "Brandes", "age": 44 },
  { "id": "b65678c2", "name": "Sawyer", "age": 78 },
  { "id": "17bb2091", "name": "Berlin", "age": 63 },
  { "id": "a03beade", "name": "Aldric", "age": 66 },
  { "id": "36a14707", "name": "Rosene", "age": 39 },
  { "id": "81937c6", "name": "Christmann", "age": 72 },
  { "id": "f990bab6", "name": "Mischa", "age": 72 },
  { "id": "dc4474c8", "name": "Joachim", "age": 70 },
  { "id": "2becd9bf", "name": "Litton", "age": 43 },
  { "id": "a00902c6", "name": "Christopher", "age": 50 },
  { "id": "6c0ea2d9", "name": "Orlov", "age": 37 },
  { "id": "7f0d400f", "name": "Harbert", "age": 55 },
  { "id": "4aaf7646", "name": "Thema", "age": 58 },
  { "id": "c5f796e4", "name": "Havener", "age": 58 },
  { "id": "1fa22377", "name": "Nata", "age": 63 },
  { "id": "dcc5dd39", "name": "Ariana", "age": 31 },
  { "id": "3fc1e0b6", "name": "Charmion", "age": 38 },
  { "id": "2aeb2746", "name": "Oberheim", "age": 82 },
  { "id": "96686659", "name": "Gage", "age": 31 },
  { "id": "6ac2db7b", "name": "Gearard", "age": 53 },
  { "id": "464e14f3", "name": "Hoi", "age": 47 },
  { "id": "1cc5a98a", "name": "Maurey", "age": 48 },
  { "id": "167d1234", "name": "Pulcheria", "age": 48 },
  { "id": "b267ccae", "name": "Herv", "age": 60 },
  { "id": "99ecfa6e", "name": "Linsk", "age": 50 },
  { "id": "8d65e57a", "name": "Coshow", "age": 74 },
  { "id": "2a13934a", "name": "Mosora", "age": 58 },
  { "id": "dbc66f29", "name": "Trow", "age": 45 },
  { "id": "7e42d9ab", "name": "Mathew", "age": 81 },
  { "id": "7c583fdf", "name": "Dorotea", "age": 49 },
  { "id": "f148e5a3", "name": "Parlin", "age": 31 },
  { "id": "3ed53de0", "name": "Al", "age": 76 },
  { "id": "cb187bb", "name": "Colville", "age": 17 },
  { "id": "7b7e071c", "name": "Leticia", "age": 20 },
  { "id": "3e28b698", "name": "Grata", "age": 72 },
  { "id": "e1a9753c", "name": "Wiese", "age": 22 },
  { "id": "444d216a", "name": "Raquela", "age": 70 },
  { "id": "365d9975", "name": "Danyette", "age": 33 },
  { "id": "f4fa6caa", "name": "Naarah", "age": 18 },
  { "id": "f79defb1", "name": "Kassity", "age": 51 },
  { "id": "26062ade", "name": "Steven", "age": 64 },
  { "id": "c6aedde8", "name": "Beach", "age": 26 },
  { "id": "3ee04dea", "name": "Dallis", "age": 18 },
  { "id": "d056c817", "name": "Grounds", "age": 43 },
  { "id": "415a99a9", "name": "Marx", "age": 83 },
  { "id": "9941ab8f", "name": "Mariand", "age": 83 },
  { "id": "3495af59", "name": "Nicola", "age": 21 },
  { "id": "fe646c20", "name": "Maroney", "age": 80 },
  { "id": "98e21f59", "name": "Bomke", "age": 49 },
  { "id": "b107d85b", "name": "Sergo", "age": 77 },
  { "id": "60c221a3", "name": "Matthia", "age": 67 },
  { "id": "bbe82dbf", "name": "Caputto", "age": 51 },
  { "id": "92b1d67f", "name": "Vittoria", "age": 85 },
  { "id": "b0166097", "name": "Asuncion", "age": 71 },
  { "id": "effcb357", "name": "Gayle", "age": 43 },
  { "id": "76b4ce4d", "name": "Pampuch", "age": 37 },
  { "id": "386a9653", "name": "Elaine", "age": 71 },
  { "id": "c15bd4a0", "name": "Mide", "age": 62 },
  { "id": "5a3cb458", "name": "Brace", "age": 54 },
  { "id": "71eff03d", "name": "Antonella", "age": 39 },
  { "id": "3290e4f9", "name": "Pickford", "age": 17 },
  { "id": "2c150c2a", "name": "Lomax", "age": 80 },
  { "id": "5ec68579", "name": "Norvun", "age": 67 },
  { "id": "f2616fb8", "name": "Klemens", "age": 30 },
  { "id": "9d9a4839", "name": "Calloway", "age": 21 },
  { "id": "5a39b756", "name": "Lawler", "age": 72 },
  { "id": "80c87b9b", "name": "Vernice", "age": 57 },
  { "id": "95633f4c", "name": "Julian", "age": 68 },
  { "id": "de1661fb", "name": "Arvin", "age": 53 },
  { "id": "449c29c1", "name": "Robinetta", "age": 39 },
  { "id": "c46cbc10", "name": "Aziza", "age": 34 },
  { "id": "c9cad62d", "name": "Bunde", "age": 73 },
  { "id": "f79824d4", "name": "Bruce", "age": 48 },
  { "id": "385d3bc8", "name": "Mallin", "age": 64 },
  { "id": "3a65face", "name": "Hurlow", "age": 26 },
  { "id": "d4b91706", "name": "Ettari", "age": 52 },
  { "id": "15c0cb29", "name": "Porcia", "age": 63 },
  { "id": "1d24779c", "name": "Aenneea", "age": 56 },
  { "id": "16ec9440", "name": "Maitilde", "age": 46 },
  { "id": "3163dd34", "name": "Curhan", "age": 72 },
  { "id": "8f3aa298", "name": "Kassab", "age": 46 },
  { "id": "b51951f7", "name": "Casanova", "age": 55 },
  { "id": "ebc6d479", "name": "Dolores", "age": 27 },
  { "id": "a6a3b9f9", "name": "Khorma", "age": 69 },
  { "id": "82d37914", "name": "Elianore", "age": 78 },
  { "id": "4c2bc58d", "name": "Wenoa", "age": 43 },
  { "id": "db2cb7b8", "name": "Maidie", "age": 56 },
  { "id": "931d20c5", "name": "Rovit", "age": 21 },
  { "id": "83abc73", "name": "Partan", "age": 55 },
  { "id": "56216866", "name": "Gerianna", "age": 56 },
  { "id": "13f14c0a", "name": "Lenee", "age": 82 },
  { "id": "2e5ef677", "name": "Mandelbaum", "age": 51 },
  { "id": "3feadd80", "name": "Sheffy", "age": 82 },
  { "id": "39c493b8", "name": "Angle", "age": 40 },
  { "id": "b959e73a", "name": "Carmine", "age": 24 },
  { "id": "f66ffd93", "name": "Meara", "age": 33 },
  { "id": "ec17344d", "name": "Boonie", "age": 79 },
  { "id": "8385f579", "name": "Healey", "age": 51 },
  { "id": "3c707277", "name": "Nelan", "age": 21 },
  { "id": "56de244c", "name": "Norman", "age": 66 },
  { "id": "71feb272", "name": "Carmena", "age": 70 },
  { "id": "b1a3d259", "name": "Roath", "age": 55 },
  { "id": "bca3294", "name": "Ready", "age": 72 },
  { "id": "272a9923", "name": "Hoisch", "age": 65 },
  { "id": "3ded2079", "name": "Miguela", "age": 37 },
  { "id": "ca2a158a", "name": "Nelrsa", "age": 34 },
  { "id": "dbb45630", "name": "Daune", "age": 84 },
  { "id": "72573e35", "name": "Sibley", "age": 17 },
  { "id": "d3e42b71", "name": "Riggall", "age": 51 },
  { "id": "e9af0516", "name": "Attlee", "age": 46 },
  { "id": "e533e86b", "name": "Maletta", "age": 45 },
  { "id": "d9d59f55", "name": "Greenstein", "age": 85 },
  { "id": "d991bcb5", "name": "Molloy", "age": 77 },
  { "id": "bd19f5ad", "name": "Bevin", "age": 43 },
  { "id": "6f7f5d56", "name": "Macnair", "age": 48 },
  { "id": "59f34fc5", "name": "Gaspar", "age": 19 },
  { "id": "57814dba", "name": "Sacci", "age": 50 },
  { "id": "96a04c49", "name": "Dreher", "age": 65 },
  { "id": "d87fe8f0", "name": "Moselle", "age": 16 },
  { "id": "42bd122e", "name": "Cottrell", "age": 60 },
  { "id": "eb73ef3b", "name": "Denice", "age": 19 },
  { "id": "e642b69b", "name": "Psyche", "age": 29 },
  { "id": "642f79e9", "name": "Seligmann", "age": 17 },
  { "id": "de89683f", "name": "Moitoso", "age": 67 },
  { "id": "55186c11", "name": "Col", "age": 45 },
  { "id": "b389bf08", "name": "Rad", "age": 16 },
  { "id": "7e2b48af", "name": "Apthorp", "age": 47 },
  { "id": "54698169", "name": "Kwok", "age": 49 },
  { "id": "9c8f2ab5", "name": "Meridith", "age": 23 },
  { "id": "48a2baca", "name": "Rennane", "age": 28 },
  { "id": "79c80c47", "name": "Madora", "age": 75 },
  { "id": "f0677852", "name": "Rebecca", "age": 16 },
  { "id": "fcd2ab8c", "name": "Wane", "age": 84 },
  { "id": "f9bd082e", "name": "Philips", "age": 28 },
  { "id": "bdd16938", "name": "Bil", "age": 70 },
  { "id": "1c771120", "name": "Amitie", "age": 32 },
  { "id": "cfe53e5b", "name": "Domph", "age": 75 },
  { "id": "2567cce1", "name": "Grunberg", "age": 75 },
  { "id": "b346e6e5", "name": "Nassir", "age": 49 },
  { "id": "9836fbfc", "name": "Farrish", "age": 20 },
  { "id": "d8c0c0f7", "name": "Penrose", "age": 63 },
  { "id": "38f62a7d", "name": "Cassie", "age": 45 },
  { "id": "bdfe7738", "name": "Blunt", "age": 34 },
  { "id": "82e3b4b", "name": "Misha", "age": 49 },
  { "id": "f793d7a5", "name": "Brody", "age": 35 },
  { "id": "c14d61b2", "name": "Juetta", "age": 26 },
  { "id": "1b049563", "name": "Reseda", "age": 25 },
  { "id": "3f417d63", "name": "Schlessinger", "age": 73 },
  { "id": "6cc804ce", "name": "Keegan", "age": 74 },
  { "id": "b9b7702", "name": "Tor", "age": 38 },
  { "id": "a46b720a", "name": "Markos", "age": 76 },
  { "id": "7bf4e332", "name": "Vaughn", "age": 80 },
  { "id": "951d0df4", "name": "Salsbury", "age": 36 },
  { "id": "aedc5eee", "name": "Kimura", "age": 82 },
  { "id": "715c5621", "name": "Samuella", "age": 25 },
  { "id": "1bd40d91", "name": "Clarinda", "age": 83 },
  { "id": "d2710d09", "name": "Shult", "age": 51 },
  { "id": "ce799e70", "name": "Kosse", "age": 18 },
  { "id": "9ad5b435", "name": "Jarrad", "age": 81 },
  { "id": "26fe6991", "name": "Cirilo", "age": 63 },
  { "id": "d7b9d583", "name": "Woodsum", "age": 65 },
  { "id": "8e89ce53", "name": "Queri", "age": 79 },
  { "id": "fda33d37", "name": "Rozalie", "age": 33 },
  { "id": "cf3fe023", "name": "Magda", "age": 55 },
  { "id": "49ca0b0", "name": "Brighton", "age": 42 },
  { "id": "79db682d", "name": "Vidovic", "age": 35 },
  { "id": "5b861e7", "name": "Grieve", "age": 63 },
  { "id": "5f471cbb", "name": "Kalinda", "age": 27 },
  { "id": "e3050455", "name": "Dulcia", "age": 67 },
  { "id": "bac47c69", "name": "Watson", "age": 47 },
  { "id": "4eb8214f", "name": "Troyes", "age": 85 },
  { "id": "32ed9e2c", "name": "Urbas", "age": 40 },
  { "id": "d650652c", "name": "Eisele", "age": 40 },
  { "id": "db163ba8", "name": "Yank", "age": 74 },
  { "id": "b8cf77ae", "name": "Milan", "age": 60 },
  { "id": "8514b5c4", "name": "Christianity", "age": 66 },
  { "id": "14994625", "name": "Arin", "age": 71 },
  { "id": "64ff7c2", "name": "Mahan", "age": 32 },
  { "id": "9503b2f8", "name": "Applegate", "age": 74 },
  { "id": "2cab0efa", "name": "Osi", "age": 50 },
  { "id": "3aa20ebe", "name": "Anthony", "age": 70 },
  { "id": "c0d586f9", "name": "Atcliffe", "age": 19 },
  { "id": "f8485368", "name": "Soraya", "age": 18 },
  { "id": "754c5093", "name": "Ruffin", "age": 31 },
  { "id": "89f3cddf", "name": "Gaither", "age": 79 },
  { "id": "45a83307", "name": "Kulsrud", "age": 51 },
  { "id": "305ae86b", "name": "Darell", "age": 33 },
  { "id": "6816df99", "name": "Rocray", "age": 33 },
  { "id": "281f181d", "name": "Dimmick", "age": 75 },
  { "id": "385a8b7e", "name": "Mara", "age": 52 },
  { "id": "854ae0ef", "name": "Gerrie", "age": 81 },
  { "id": "a4d0dc3e", "name": "Steinke", "age": 40 },
  { "id": "3464fbac", "name": "Sparhawk", "age": 16 },
  { "id": "3ff997b6", "name": "Tillfourd", "age": 26 },
  { "id": "b62401c", "name": "Ewald", "age": 52 },
  { "id": "87edb1b0", "name": "Qulllon", "age": 46 },
  { "id": "e87b88ac", "name": "Ardisj", "age": 34 },
  { "id": "ecb1f335", "name": "Tadashi", "age": 35 },
  { "id": "714ce71", "name": "Algernon", "age": 27 },
  { "id": "afd9b85f", "name": "Genisia", "age": 77 },
  { "id": "44a7aa5a", "name": "Puduns", "age": 26 },
  { "id": "dd4a58a6", "name": "Olga", "age": 70 },
  { "id": "c3cdbf0d", "name": "Horten", "age": 75 },
  { "id": "fcef5ac6", "name": "Olenta", "age": 30 },
  { "id": "a9498aa9", "name": "Ruel", "age": 65 },
  { "id": "26b8068b", "name": "Rafat", "age": 53 },
  { "id": "545a1718", "name": "Quickman", "age": 32 },
  { "id": "89aa8d47", "name": "Rebah", "age": 85 },
  { "id": "3897d94e", "name": "Cadel", "age": 18 },
  { "id": "d0569888", "name": "Kippy", "age": 48 },
  { "id": "16c04bd5", "name": "Dean", "age": 53 },
  { "id": "edcd5c5", "name": "Rafi", "age": 35 },
  { "id": "f56fae34", "name": "Mila", "age": 48 },
  { "id": "a45d3a81", "name": "Roxy", "age": 55 },
  { "id": "20164f23", "name": "Alejandro", "age": 79 },
  { "id": "81b1420e", "name": "Knowling", "age": 42 },
  { "id": "2c6f5b2d", "name": "Chen", "age": 47 },
  { "id": "2d11bbf5", "name": "Gwenny", "age": 45 },
  { "id": "4f8f25c", "name": "Erminie", "age": 22 },
  { "id": "d33a3ade", "name": "Primo", "age": 20 },
  { "id": "f6a42596", "name": "Madelina", "age": 48 },
  { "id": "ebf862ad", "name": "Lyndon", "age": 45 },
  { "id": "9d9dc599", "name": "Helm", "age": 35 },
  { "id": "cfde1c8e", "name": "Rodmun", "age": 60 },
  { "id": "d139f55c", "name": "Bubalo", "age": 74 },
  { "id": "ad8f3076", "name": "Pincince", "age": 78 },
  { "id": "bc09cf52", "name": "Friday", "age": 82 },
  { "id": "28e80feb", "name": "Edyth", "age": 73 },
  { "id": "eab6a822", "name": "Rosenblast", "age": 74 },
  { "id": "fe494181", "name": "Berns", "age": 77 },
  { "id": "857ed289", "name": "Norah", "age": 27 },
  { "id": "27dff334", "name": "Belldas", "age": 48 },
  { "id": "5fa4d0e2", "name": "Ofella", "age": 34 },
  { "id": "e3d43d79", "name": "Stillas", "age": 17 },
  { "id": "3f5fe3b3", "name": "Levan", "age": 75 },
  { "id": "43cb92a1", "name": "Pete", "age": 23 },
  { "id": "addee65a", "name": "Asha", "age": 26 },
  { "id": "eaa8ae78", "name": "Rodolphe", "age": 72 },
  { "id": "1c7a6231", "name": "Pacian", "age": 43 },
  { "id": "a43bb097", "name": "Kattie", "age": 61 },
  { "id": "cc42a89a", "name": "Hayyim", "age": 58 },
  { "id": "8d3f41f2", "name": "Lawtun", "age": 22 },
  { "id": "115d02b7", "name": "Diego", "age": 81 },
  { "id": "2035320a", "name": "Pliam", "age": 56 },
  { "id": "4587d3b1", "name": "Almita", "age": 53 },
  { "id": "ffb1330c", "name": "Lisha", "age": 36 },
  { "id": "b912eb6f", "name": "Lewes", "age": 35 },
  { "id": "f0ea0167", "name": "Pesek", "age": 19 },
  { "id": "b43841ff", "name": "Younglove", "age": 67 },
  { "id": "900f0cce", "name": "Jacobina", "age": 38 },
  { "id": "f1cd219", "name": "Feodore", "age": 49 },
  { "id": "f8d3599b", "name": "Farny", "age": 49 },
  { "id": "4824ebbe", "name": "Akin", "age": 44 },
  { "id": "aa991035", "name": "Andersen", "age": 63 },
  { "id": "8d442e16", "name": "Urbani", "age": 58 },
  { "id": "39d41653", "name": "Madson", "age": 45 },
  { "id": "8dc1c1b3", "name": "Simonetta", "age": 17 },
  { "id": "4aaf7646", "name": "Thema", "age": 58 },
  { "id": "9dc042a3", "name": "Milks", "age": 39 },
  { "id": "c7e046bb", "name": "Costa", "age": 31 },
  { "id": "8f116482", "name": "Ivatts", "age": 16 },
  { "id": "8d200ddf", "name": "Romelda", "age": 55 },
  { "id": "59718bae", "name": "Wells", "age": 46 },
  { "id": "2b8d51ce", "name": "Fen", "age": 52 },
  { "id": "c992d96e", "name": "Barbabra", "age": 80 },
  { "id": "8ded232a", "name": "Tarr", "age": 36 },
  { "id": "bec66275", "name": "Lindeberg", "age": 19 },
  { "id": "7fa2b5d5", "name": "Omari", "age": 39 },
  { "id": "ccc14292", "name": "Gibun", "age": 50 },
  { "id": "9bc12ef9", "name": "Fleisher", "age": 59 },
  { "id": "4331b6a4", "name": "Lowell", "age": 58 },
  { "id": "9c96d985", "name": "Stephana", "age": 17 },
  { "id": "5e34b18c", "name": "Bowen", "age": 54 },
  { "id": "c2efb2bf", "name": "McFerren", "age": 23 },
  { "id": "e24e77be", "name": "Gentry", "age": 84 },
  { "id": "34e50b7c", "name": "Emilie", "age": 22 },
  { "id": "e9c007b", "name": "Artemisa", "age": 59 },
  { "id": "dcc0baae", "name": "Greggs", "age": 68 },
  { "id": "605daada", "name": "Edithe", "age": 48 },
  { "id": "8a130a1", "name": "Antonino", "age": 69 },
  { "id": "3d4f3c5", "name": "Lukash", "age": 51 },
  { "id": "c34289c4", "name": "Joeann", "age": 30 },
  { "id": "55616979", "name": "Vera", "age": 59 },
  { "id": "2222fef7", "name": "Banquer", "age": 65 },
  { "id": "ac651188", "name": "Salomo", "age": 62 },
  { "id": "c2da4a76", "name": "Burt", "age": 80 },
  { "id": "f4fa6caa", "name": "Naarah", "age": 18 },
  { "id": "9cab1f0f", "name": "Ibrahim", "age": 79 },
  { "id": "699246fb", "name": "McNelly", "age": 83 },
  { "id": "993014d9", "name": "Weight", "age": 79 },
  { "id": "7514206e", "name": "Shyamal", "age": 40 },
  { "id": "40bc51c7", "name": "Sil", "age": 83 },
  { "id": "5b2dcafa", "name": "Annadiane", "age": 44 },
  { "id": "1d442ac1", "name": "Shipman", "age": 73 },
  { "id": "a4c8b513", "name": "Mosra", "age": 35 },
  { "id": "7c79b256", "name": "Bathilda", "age": 60 },
  { "id": "3a9d6", "name": "Amice", "age": 72 },
  { "id": "64f92c97", "name": "Barbe", "age": 45 },
  { "id": "1fd9943b", "name": "Krisha", "age": 61 },
  { "id": "5c6c9a71", "name": "Mohl", "age": 73 },
  { "id": "e55ab2b1", "name": "Amersham", "age": 75 },
  { "id": "f8094026", "name": "Agle", "age": 30 },
  { "id": "7a5dbaa7", "name": "Codd", "age": 59 },
  { "id": "3c700735", "name": "Pacien", "age": 73 },
  { "id": "acf04d96", "name": "Grizel", "age": 20 },
  { "id": "1c73f224", "name": "Sarajane", "age": 32 },
  { "id": "f3e2a6fe", "name": "Desi", "age": 40 },
  { "id": "3914a87f", "name": "Meador", "age": 23 },
  { "id": "51627685", "name": "Noyes", "age": 51 },
  { "id": "91488b07", "name": "Humphrey", "age": 49 },
  { "id": "3b611b9e", "name": "Matta", "age": 52 },
  { "id": "3c8eafc8", "name": "Condon", "age": 28 },
  { "id": "d64ece58", "name": "Varini", "age": 52 },
  { "id": "a6803351", "name": "Erle", "age": 37 },
  { "id": "f5751eac", "name": "Charry", "age": 80 },
  { "id": "6a1da6ef", "name": "Harty", "age": 61 },
  { "id": "1cbc2f09", "name": "Blackington", "age": 43 },
  { "id": "9873d84", "name": "Israeli", "age": 48 },
  { "id": "b84cc01a", "name": "Gatias", "age": 54 },
  { "id": "8f800bfc", "name": "Anastasia", "age": 60 },
  { "id": "e0740cf5", "name": "Uball", "age": 23 },
  { "id": "c28ad649", "name": "Zondra", "age": 85 },
  { "id": "9f66109b", "name": "Amado", "age": 73 },
  { "id": "99d289b1", "name": "Ellswerth", "age": 33 },
  { "id": "66fd3cb1", "name": "Donell", "age": 33 },
  { "id": "8a3ef5da", "name": "Grayce", "age": 34 },
  { "id": "adb327ba", "name": "Miguelita", "age": 28 },
  { "id": "6e546b0b", "name": "MacFarlane", "age": 33 },
  { "id": "347abd92", "name": "Ruprecht", "age": 80 },
  { "id": "513a4946", "name": "Raphael", "age": 78 },
  { "id": "e77abab0", "name": "Scharf", "age": 46 },
  { "id": "a6d9ebfb", "name": "Inerney", "age": 85 },
  { "id": "e7e9b8a", "name": "Andria", "age": 74 },
  { "id": "bdafe1e2", "name": "Schechinger", "age": 36 },
  { "id": "96111d4f", "name": "Hawger", "age": 31 },
  { "id": "d8ca612a", "name": "Rayford", "age": 58 },
  { "id": "3728c63c", "name": "Dwain", "age": 44 },
  { "id": "d7affdc", "name": "Daffie", "age": 36 },
  { "id": "9565aa56", "name": "Lacombe", "age": 62 },
  { "id": "766ec227", "name": "Milissent", "age": 77 },
  { "id": "928b9bbb", "name": "Lorne", "age": 43 },
  { "id": "f3b1dc3f", "name": "Ozen", "age": 79 },
  { "id": "b6738402", "name": "Malamut", "age": 62 },
  { "id": "c7145eb5", "name": "Randa", "age": 35 },
  { "id": "53208ebe", "name": "Ruttger", "age": 18 },
  { "id": "b9e36316", "name": "Patsy", "age": 44 },
  { "id": "c3946600", "name": "Murdock", "age": 26 },
  { "id": "2dac43c9", "name": "Albin", "age": 41 },
  { "id": "1e27d028", "name": "Vyky", "age": 58 },
  { "id": "b0e34f7", "name": "Gylys", "age": 55 },
  { "id": "2a44989a", "name": "Adiel", "age": 32 },
  { "id": "3e71e3bc", "name": "Dannye", "age": 56 },
  { "id": "2f0c9cb5", "name": "Elva", "age": 17 },
  { "id": "19a486f7", "name": "Arbe", "age": 81 },
  { "id": "1102166a", "name": "Cesaro", "age": 28 },
  { "id": "e0c5e385", "name": "Ariane", "age": 37 },
  { "id": "c284ac35", "name": "Mikal", "age": 67 },
  { "id": "44cf8198", "name": "McDowell", "age": 32 },
  { "id": "db4eff94", "name": "Jenn", "age": 26 },
  { "id": "b0bcfd71", "name": "Tori", "age": 41 },
  { "id": "2a62a757", "name": "Winston", "age": 85 },
  { "id": "c7b363e2", "name": "Bev", "age": 54 },
  { "id": "6f9886f3", "name": "Eusebio", "age": 41 },
  { "id": "2ba71600", "name": "Say", "age": 68 },
  { "id": "41a9e345", "name": "Pontius", "age": 31 },
  { "id": "31776629", "name": "Shayne", "age": 17 },
  { "id": "87119311", "name": "Pollerd", "age": 27 },
  { "id": "1e12281a", "name": "Althee", "age": 30 },
  { "id": "3bfee718", "name": "Satterlee", "age": 54 },
  { "id": "48499aeb", "name": "Hak", "age": 35 },
  { "id": "b3e4d1a5", "name": "Desmond", "age": 77 },
  { "id": "76be677c", "name": "Warford", "age": 56 },
  { "id": "22d27b53", "name": "Lumpkin", "age": 51 },
  { "id": "384df2c2", "name": "Hurley", "age": 30 },
  { "id": "55df2924", "name": "Gabriello", "age": 26 },
  { "id": "c5fabab9", "name": "Neri", "age": 39 },
  { "id": "bf48de8b", "name": "Ciapha", "age": 55 },
  { "id": "d566b72", "name": "Caryn", "age": 36 },
  { "id": "125601fc", "name": "Schuh", "age": 28 },
  { "id": "acd90155", "name": "Hedda", "age": 81 },
  { "id": "102f1f5d", "name": "Thomas", "age": 63 },
  { "id": "afa42fe4", "name": "Yeo", "age": 60 },
  { "id": "d0bc486f", "name": "Barthel", "age": 75 },
  { "id": "41d9a4e4", "name": "Bouldon", "age": 20 },
  { "id": "5bef036d", "name": "Ku", "age": 83 },
  { "id": "47a8412e", "name": "Dunn", "age": 36 },
  { "id": "3c156f2a", "name": "Klusek", "age": 30 },
  { "id": "29d704e1", "name": "Chubb", "age": 21 },
  { "id": "5c6d879f", "name": "Wooldridge", "age": 31 },
  { "id": "bccabc86", "name": "Baiel", "age": 38 },
  { "id": "7e9e9523", "name": "Somerville", "age": 39 },
  { "id": "29afb5ec", "name": "Boycie", "age": 44 },
  { "id": "7bcaa163", "name": "Margret", "age": 61 },
  { "id": "1c73f224", "name": "Sarajane", "age": 32 },
  { "id": "ae4e0bdc", "name": "Wilbert", "age": 64 },
  { "id": "248ef756", "name": "Heidy", "age": 52 },
  { "id": "6a264700", "name": "Ludlow", "age": 76 },
  { "id": "fcf49346", "name": "Aliza", "age": 84 },
  { "id": "8685fdf5", "name": "Cohlette", "age": 21 },
  { "id": "aa0e582e", "name": "Candi", "age": 24 },
  { "id": "e5c00b58", "name": "Lawrence", "age": 26 },
  { "id": "462220db", "name": "Kaliski", "age": 81 },
  { "id": "279134d4", "name": "Alarick", "age": 44 },
  { "id": "6f407bb4", "name": "Shane", "age": 24 },
  { "id": "2c15fb03", "name": "Ober", "age": 45 },
  { "id": "47f55a61", "name": "Blain", "age": 19 },
  { "id": "8328421c", "name": "Foushee", "age": 36 },
  { "id": "35b5ce7c", "name": "Donovan", "age": 70 },
  { "id": "856fbbc6", "name": "Hyman", "age": 50 },
  { "id": "44fbfd39", "name": "Ilowell", "age": 45 },
  { "id": "8214b478", "name": "Serrell", "age": 46 },
  { "id": "1eef38f9", "name": "Alberik", "age": 45 },
  { "id": "8ef1fece", "name": "Iseabal", "age": 84 },
  { "id": "eb3261bf", "name": "Egide", "age": 69 },
  { "id": "4c8045be", "name": "Parrish", "age": 44 },
  { "id": "b3bfdcae", "name": "Gus", "age": 70 },
  { "id": "7c3c7c6e", "name": "Meece", "age": 54 },
  { "id": "9610ea15", "name": "Anjanette", "age": 77 },
  { "id": "e706694e", "name": "Greenburg", "age": 36 },
  { "id": "37a17758", "name": "Heathcote", "age": 54 },
  { "id": "5f78d738", "name": "Mariam", "age": 42 },
  { "id": "418d545a", "name": "Lower", "age": 26 },
  { "id": "be8c4d2f", "name": "Quincey", "age": 85 },
  { "id": "7aa6acef", "name": "Ribal", "age": 25 },
  { "id": "9731afc3", "name": "Starinsky", "age": 61 },
  { "id": "f433b980", "name": "Kylen", "age": 54 },
  { "id": "8ba256d5", "name": "Jennings", "age": 21 },
  { "id": "b3d390d8", "name": "Beale", "age": 16 },
  { "id": "917eb50", "name": "Greenwald", "age": 48 },
  { "id": "c70fc3c5", "name": "Diann", "age": 67 },
  { "id": "5e15293a", "name": "Gustafsson", "age": 80 },
  { "id": "cb6c1be8", "name": "Garzon", "age": 26 },
  { "id": "c7846e95", "name": "Marco", "age": 81 },
  { "id": "ddaa9265", "name": "Jentoft", "age": 79 },
  { "id": "2eb5d028", "name": "Teahan", "age": 36 },
  { "id": "f357f7d7", "name": "Fenner", "age": 33 },
  { "id": "8f1570e5", "name": "Ximenez", "age": 31 },
  { "id": "7cbedc51", "name": "Letitia", "age": 81 },
  { "id": "f795a4f7", "name": "Karrie", "age": 43 },
  { "id": "79389385", "name": "Seana", "age": 53 },
  { "id": "3c5460ea", "name": "Mildred", "age": 50 },
  { "id": "2c47a69a", "name": "Shaver", "age": 26 },
  { "id": "89789100", "name": "Benedicta", "age": 28 },
  { "id": "5a384183", "name": "Nikos", "age": 63 },
  { "id": "b192e681", "name": "Alfred", "age": 43 },
  { "id": "7bbdc4f", "name": "Philan", "age": 19 },
  { "id": "4c893d32", "name": "Alene", "age": 30 },
  { "id": "7c7b9e7e", "name": "Rocher", "age": 52 },
  { "id": "ccdb4ad9", "name": "Slyke", "age": 65 },
  { "id": "a90c9502", "name": "Cattan", "age": 58 },
  { "id": "c271b815", "name": "Pratte", "age": 73 },
  { "id": "d7d8faf6", "name": "Bruning", "age": 68 },
  { "id": "30ae80e", "name": "Elston", "age": 50 },
  { "id": "b0fc69de", "name": "Freberg", "age": 36 },
  { "id": "18024f63", "name": "Holmes", "age": 25 },
  { "id": "4fb3851a", "name": "Haily", "age": 38 },
  { "id": "8a8951e0", "name": "Niela", "age": 66 },
  { "id": "57691219", "name": "Orji", "age": 81 },
  { "id": "1e3fafeb", "name": "Dublin", "age": 29 },
  { "id": "20c2d692", "name": "Ettie", "age": 52 },
  { "id": "b398ce74", "name": "Flanders", "age": 74 },
  { "id": "528e5426", "name": "McCutcheon", "age": 42 },
  { "id": "bbb14992", "name": "Jeniffer", "age": 64 },
  { "id": "af619fe8", "name": "Leia", "age": 84 },
  { "id": "a1cce7c3", "name": "Inna", "age": 17 },
  { "id": "b71fcd51", "name": "Mastat", "age": 21 },
  { "id": "ec3740ad", "name": "Onofredo", "age": 49 },
  { "id": "3fff4a1c", "name": "Grefer", "age": 66 },
  { "id": "1c83f4ad", "name": "Ramona", "age": 27 },
  { "id": "d979b7cf", "name": "Mollee", "age": 49 },
  { "id": "ede89807", "name": "Frolick", "age": 79 },
  { "id": "e7cd4e77", "name": "Jessamyn", "age": 59 },
  { "id": "90320ee8", "name": "Achorn", "age": 16 },
  { "id": "ae398d55", "name": "Penelopa", "age": 43 },
  { "id": "7589c368", "name": "Takashi", "age": 24 },
  { "id": "a693452c", "name": "Maren", "age": 82 },
  { "id": "553d1a72", "name": "Franek", "age": 42 },
  { "id": "920168b7", "name": "Vareck", "age": 35 },
  { "id": "1952eabe", "name": "Allsopp", "age": 22 },
  { "id": "c71bcd68", "name": "Atlante", "age": 66 },
  { "id": "de3d7955", "name": "Persse", "age": 75 },
  { "id": "54e3a59", "name": "Aubrie", "age": 71 },
  { "id": "78c528ab", "name": "Romney", "age": 49 },
  { "id": "fccc9de7", "name": "Sibella", "age": 65 },
  { "id": "e888217d", "name": "Clementina", "age": 77 },
  { "id": "52af6c73", "name": "Petronille", "age": 71 },
  { "id": "5be2377a", "name": "Lu", "age": 40 },
  { "id": "6c75c845", "name": "Bobbe", "age": 65 },
  { "id": "d55bd9ff", "name": "Ide", "age": 57 },
  { "id": "c43f57cd", "name": "Roda", "age": 37 },
  { "id": "e4491893", "name": "Berni", "age": 73 },
  { "id": "435c042d", "name": "Jacinda", "age": 69 },
  { "id": "880d5945", "name": "Lily", "age": 43 },
  { "id": "23a2e9e1", "name": "Elenore", "age": 41 },
  { "id": "c3fae3cd", "name": "Lepper", "age": 53 },
  { "id": "874d55b2", "name": "Waldner", "age": 46 },
  { "id": "b6bc0e42", "name": "Saimon", "age": 66 },
  { "id": "854f326e", "name": "Bowra", "age": 78 },
  { "id": "69d957a3", "name": "Fruin", "age": 23 },
  { "id": "52798a2", "name": "Forsta", "age": 64 },
  { "id": "a95841b4", "name": "Lonee", "age": 38 },
  { "id": "97249c85", "name": "Kramer", "age": 37 },
  { "id": "b94a65c5", "name": "Handbook", "age": 33 },
  { "id": "800ed611", "name": "Laurene", "age": 79 },
  { "id": "b7682ccf", "name": "Hassin", "age": 69 },
  { "id": "fc0867a7", "name": "Romain", "age": 51 },
  { "id": "e5d0fd52", "name": "Birdt", "age": 68 },
  { "id": "69dd8be3", "name": "Nasia", "age": 23 },
  { "id": "45dafdc7", "name": "Chemar", "age": 45 },
  { "id": "86fb32d9", "name": "Ary", "age": 33 },
  { "id": "af180a84", "name": "Ranee", "age": 82 },
  { "id": "20cfccef", "name": "Oba", "age": 33 },
  { "id": "7533a76f", "name": "Hiroko", "age": 27 },
  { "id": "d2ade9a1", "name": "Pippy", "age": 83 },
  { "id": "4df3f4dc", "name": "Blankenship", "age": 60 },
  { "id": "e49a1c28", "name": "Sihonn", "age": 46 },
  { "id": "b2e15e56", "name": "Alodi", "age": 84 },
  { "id": "1ad50451", "name": "Euridice", "age": 75 },
  { "id": "265c6db8", "name": "Gisser", "age": 74 },
  { "id": "85f70e41", "name": "Nerta", "age": 85 },
  { "id": "d53d9d78", "name": "Brainard", "age": 42 },
  { "id": "ce9ffd90", "name": "Dearden", "age": 58 },
  { "id": "a9163e13", "name": "Hildegard", "age": 83 },
  { "id": "d28580fd", "name": "Pazit", "age": 25 },
  { "id": "ca02df49", "name": "Danna", "age": 81 },
  { "id": "9da17aa", "name": "Gerstein", "age": 16 },
  { "id": "613e552a", "name": "Hayton", "age": 52 },
  { "id": "6f92c1d2", "name": "Drugi", "age": 36 },
  { "id": "c9464bf2", "name": "Gilchrist", "age": 24 },
  { "id": "de9ee39a", "name": "Richy", "age": 62 },
  { "id": "605f83f4", "name": "Fowle", "age": 62 },
  { "id": "ba79c4fd", "name": "Jacquelyn", "age": 67 },
  { "id": "f366472f", "name": "Legge", "age": 59 },
  { "id": "dd3b43f9", "name": "Kamal", "age": 67 },
  { "id": "c964feee", "name": "Follansbee", "age": 54 },
  { "id": "28717fd6", "name": "Clyte", "age": 80 },
  { "id": "8d4944a", "name": "Karalee", "age": 78 },
  { "id": "10d05346", "name": "Volding", "age": 38 },
  { "id": "e8e7370c", "name": "Hamel", "age": 46 },
  { "id": "f914ba9a", "name": "Zindman", "age": 20 },
  { "id": "8c7dc1f8", "name": "Weinshienk", "age": 82 },
  { "id": "941d1674", "name": "Beilul", "age": 76 },
  { "id": "82d1c0a5", "name": "Ernesto", "age": 27 },
  { "id": "4b5425c3", "name": "Dag", "age": 77 },
  { "id": "88543c5b", "name": "Eudora", "age": 77 },
  { "id": "b8653ae0", "name": "Westley", "age": 18 },
  { "id": "55d8f8c1", "name": "Glinys", "age": 73 },
  { "id": "53e8e6a7", "name": "Iy", "age": 33 },
  { "id": "4c498215", "name": "Jayson", "age": 51 },
  { "id": "ca5be204", "name": "Clea", "age": 34 },
  { "id": "c1b86b", "name": "Amarillas", "age": 55 },
  { "id": "e6884f3f", "name": "Korwin", "age": 29 },
  { "id": "8e83df20", "name": "Erma", "age": 84 },
  { "id": "eb8ddda7", "name": "Marcell", "age": 65 },
  { "id": "ffed9b49", "name": "Willms", "age": 31 },
  { "id": "e573f884", "name": "Sender", "age": 80 },
  { "id": "52488cc9", "name": "Offen", "age": 51 },
  { "id": "3ac6ffba", "name": "Gray", "age": 38 },
  { "id": "fd3ef8f4", "name": "Schulein", "age": 68 },
  { "id": "b8eb17b0", "name": "Lan", "age": 84 },
  { "id": "aa941560", "name": "Schiffman", "age": 46 },
  { "id": "6f407bb4", "name": "Shane", "age": 24 },
  { "id": "74429642", "name": "Mortimer", "age": 34 },
  { "id": "370385d", "name": "Dovev", "age": 35 },
  { "id": "b4e77271", "name": "Ander", "age": 79 },
  { "id": "c483d6f9", "name": "Kelson", "age": 81 },
  { "id": "f6071590", "name": "Tremann", "age": 84 },
  { "id": "9b4ceed0", "name": "Dorthea", "age": 48 },
  { "id": "5bf81dd6", "name": "Eimile", "age": 58 },
  { "id": "5bd070ec", "name": "Aggappe", "age": 38 },
  { "id": "302e5009", "name": "Salita", "age": 79 },
  { "id": "7ed372c8", "name": "Elianora", "age": 72 },
  { "id": "40889552", "name": "Dann", "age": 22 },
  { "id": "62724bf3", "name": "Silas", "age": 31 },
  { "id": "5d9f6f5b", "name": "Vories", "age": 45 },
  { "id": "a23bdd78", "name": "Dorfman", "age": 68 },
  { "id": "78ab9c80", "name": "Jorgensen", "age": 26 },
  { "id": "6e4585fb", "name": "Dionis", "age": 39 },
  { "id": "356d4d55", "name": "Jacinthe", "age": 85 },
  { "id": "e0f636ff", "name": "Berton", "age": 55 },
  { "id": "2b8b7a4a", "name": "Ravens", "age": 24 },
  { "id": "64c16ebb", "name": "Ledah", "age": 51 },
  { "id": "c04ae076", "name": "Brittany", "age": 54 },
  { "id": "6af26c7f", "name": "Quinta", "age": 59 },
  { "id": "b65f956e", "name": "Royo", "age": 72 },
  { "id": "b6727495", "name": "Kath", "age": 17 },
  { "id": "94261973", "name": "Savanna", "age": 77 },
  { "id": "c1f87300", "name": "Tenenbaum", "age": 52 },
  { "id": "f86fb87", "name": "Lauretta", "age": 31 },
  { "id": "bfc0bc9b", "name": "Frederiksen", "age": 77 },
  { "id": "8e80659", "name": "Starr", "age": 41 },
  { "id": "376f3181", "name": "Clerissa", "age": 65 },
  { "id": "5211fb60", "name": "Kleiman", "age": 42 },
  { "id": "1c63c2ab", "name": "Burgwell", "age": 83 },
  { "id": "efe9ab84", "name": "Chane", "age": 46 },
  { "id": "12da21b6", "name": "Stoneman", "age": 42 },
  { "id": "620178a", "name": "Meldon", "age": 50 },
  { "id": "f66082ce", "name": "Areta", "age": 74 },
  { "id": "d17dc28e", "name": "Marne", "age": 56 },
  { "id": "e83d9196", "name": "Page", "age": 64 },
  { "id": "2f9e2edf", "name": "Larkins", "age": 65 },
  { "id": "6680cd17", "name": "Concettina", "age": 69 },
  { "id": "3e275c65", "name": "Krasner", "age": 65 },
  { "id": "3308bd9c", "name": "Fields", "age": 50 },
  { "id": "ad47ecc7", "name": "Proffitt", "age": 25 },
  { "id": "21575bf0", "name": "Sperry", "age": 22 },
  { "id": "7f1fc32d", "name": "Reid", "age": 29 },
  { "id": "cee7f641", "name": "Nierman", "age": 39 },
  { "id": "e7a8b246", "name": "Lunnete", "age": 28 },
  { "id": "eb5782d", "name": "Kirsti", "age": 21 },
  { "id": "f397f539", "name": "Deron", "age": 37 },
  { "id": "b8c341c9", "name": "Francie", "age": 71 },
  { "id": "a6b325a2", "name": "Scheck", "age": 80 },
  { "id": "d85b0570", "name": "Guidotti", "age": 70 },
  { "id": "36d8777e", "name": "Clinton", "age": 26 },
  { "id": "2fb8f9e1", "name": "Charlie", "age": 21 },
  { "id": "19c17209", "name": "Valerye", "age": 17 },
  { "id": "a530c053", "name": "Kiernan", "age": 29 },
  { "id": "45a554a4", "name": "Boycey", "age": 68 },
  { "id": "dd85924e", "name": "Pazia", "age": 24 },
  { "id": "aacb624b", "name": "Hinda", "age": 37 },
  { "id": "7657e7c3", "name": "Rist", "age": 27 },
  { "id": "6458584", "name": "Malcolm", "age": 26 },
  { "id": "84e8993", "name": "Frerichs", "age": 21 },
  { "id": "ccbc661d", "name": "Bac", "age": 39 },
  { "id": "71ac3dbd", "name": "Richers", "age": 31 },
  { "id": "5b533f33", "name": "Hardin", "age": 79 },
  { "id": "c2fcad9", "name": "Postman", "age": 69 },
  { "id": "189ca0c1", "name": "Nazler", "age": 79 },
  { "id": "c2aac706", "name": "Hannus", "age": 50 },
  { "id": "698abf82", "name": "Cory", "age": 80 },
  { "id": "d3be5ae8", "name": "Amelia", "age": 44 },
  { "id": "401dad63", "name": "Elephus", "age": 61 },
  { "id": "d82cf676", "name": "Mendez", "age": 50 },
  { "id": "54dbb7fe", "name": "Alia", "age": 26 },
  { "id": "4f1b270", "name": "Banebrudge", "age": 66 },
  { "id": "6feb572f", "name": "Azeria", "age": 61 },
  { "id": "7afd353b", "name": "Mauldon", "age": 33 },
  { "id": "f951cbd3", "name": "Sivie", "age": 85 },
  { "id": "fa7b8ba3", "name": "Uttica", "age": 41 },
  { "id": "d3e01e7b", "name": "Poppy", "age": 29 },
  { "id": "fbec016d", "name": "Gennifer", "age": 33 },
  { "id": "d50dd7d6", "name": "Kobylak", "age": 76 },
  { "id": "3ca33cf3", "name": "Zumwalt", "age": 17 },
  { "id": "194e6bce", "name": "Fulks", "age": 82 },
  { "id": "a065b7fd", "name": "Dorin", "age": 33 },
  { "id": "29e3c073", "name": "Upshaw", "age": 71 },
  { "id": "4f438a4a", "name": "Cychosz", "age": 64 },
  { "id": "ef940ac7", "name": "Ralli", "age": 27 },
  { "id": "9891235", "name": "Halpern", "age": 53 },
  { "id": "d9cd4de3", "name": "Landahl", "age": 37 },
  { "id": "5ef165c5", "name": "Idalina", "age": 59 },
  { "id": "6a6655c0", "name": "Aili", "age": 46 },
  { "id": "4c04b3cc", "name": "Lymann", "age": 54 },
  { "id": "eac5d69a", "name": "Rabassa", "age": 30 },
  { "id": "ef93d1f5", "name": "Colwell", "age": 41 },
  { "id": "707d53fa", "name": "Virginie", "age": 36 },
  { "id": "2e22c402", "name": "Carbo", "age": 34 },
  { "id": "eb13166e", "name": "Lindholm", "age": 32 },
  { "id": "d70875a", "name": "McGaw", "age": 36 },
  { "id": "bfdc5f19", "name": "Hannan", "age": 37 },
  { "id": "224ecf24", "name": "Justin", "age": 76 },
  { "id": "51bd1e38", "name": "Rodger", "age": 42 },
  { "id": "7a978022", "name": "Ernie", "age": 76 },
  { "id": "1214dec", "name": "Trask", "age": 18 },
  { "id": "cafc4349", "name": "Pelage", "age": 55 },
  { "id": "52dd876c", "name": "Aldwon", "age": 82 },
  { "id": "1084d6c", "name": "Staal", "age": 50 },
  { "id": "d0dc9f17", "name": "Bust", "age": 21 },
  { "id": "ca5ccf1f", "name": "Eiser", "age": 43 },
  { "id": "7e3c1775", "name": "Lathan", "age": 37 },
  { "id": "1c5c36fb", "name": "Free", "age": 51 },
  { "id": "d8ede84b", "name": "Sierra", "age": 71 },
  { "id": "95941c47", "name": "Mirth", "age": 77 },
  { "id": "c0edfd0", "name": "Brynn", "age": 78 },
  { "id": "877c29d", "name": "Derby", "age": 19 },
  { "id": "984e674d", "name": "Ridglee", "age": 71 },
  { "id": "52f23eb1", "name": "Tricia", "age": 69 },
  { "id": "3463f595", "name": "Diehl", "age": 51 },
  { "id": "c69e04e8", "name": "Maryn", "age": 78 },
  { "id": "7514206e", "name": "Shyamal", "age": 40 },
  { "id": "d909758c", "name": "Amaras", "age": 54 },
  { "id": "1183f8ed", "name": "Pirri", "age": 19 },
  { "id": "7b843c6c", "name": "Loveridge", "age": 44 },
  { "id": "3477a2e8", "name": "Clyve", "age": 66 },
  { "id": "ef7c4f17", "name": "Creedon", "age": 51 },
  { "id": "16f53302", "name": "Josefina", "age": 76 },
  { "id": "a0c0952d", "name": "Gord", "age": 67 },
  { "id": "ad96160d", "name": "Oliana", "age": 79 },
  { "id": "4c9c3e16", "name": "Stout", "age": 72 },
  { "id": "9bf57765", "name": "Lem", "age": 41 },
  { "id": "9bf7fd62", "name": "Salvatore", "age": 74 },
  { "id": "bc51310", "name": "Gorges", "age": 44 },
  { "id": "dbebcf99", "name": "Gilson", "age": 55 },
  { "id": "3e4c22f3", "name": "Lamarre", "age": 21 },
  { "id": "eed565a9", "name": "Meingolda", "age": 77 },
  { "id": "6df81544", "name": "Bryanty", "age": 52 },
  { "id": "b05aa0d4", "name": "Hinkel", "age": 34 },
  { "id": "20d0d86b", "name": "Buchbinder", "age": 49 },
  { "id": "9ccaf054", "name": "Jemima", "age": 38 },
  { "id": "8bc34de1", "name": "Brindell", "age": 77 },
  { "id": "1e7db9f9", "name": "Kunz", "age": 25 },
  { "id": "9162e2e7", "name": "Alleris", "age": 71 },
  { "id": "e11ae888", "name": "Kee", "age": 20 },
  { "id": "bfbadd65", "name": "Tilden", "age": 45 },
  { "id": "8143ff8d", "name": "Elnar", "age": 33 },
  { "id": "328859b4", "name": "Feucht", "age": 76 },
  { "id": "5e7150c", "name": "Craw", "age": 40 },
  { "id": "3d2ac1b2", "name": "Dru", "age": 40 },
  { "id": "e41291ed", "name": "Tiersten", "age": 19 },
  { "id": "e1929b2f", "name": "Xaviera", "age": 59 },
  { "id": "70ebc7c5", "name": "Ethelstan", "age": 79 },
  { "id": "bcb98ae0", "name": "Kelton", "age": 76 },
  { "id": "46c4cd66", "name": "Stanleigh", "age": 84 },
  { "id": "93152b1c", "name": "Noletta", "age": 20 },
  { "id": "a2dfafe5", "name": "Steinway", "age": 55 },
  { "id": "35ef9ef5", "name": "Thomasina", "age": 31 },
  { "id": "b26dd127", "name": "Rickart", "age": 41 },
  { "id": "1e54aca0", "name": "Bolger", "age": 82 },
  { "id": "a5c205aa", "name": "Senzer", "age": 80 },
  { "id": "8af4a35d", "name": "Tabber", "age": 29 },
  { "id": "2c61a15e", "name": "Mariande", "age": 82 },
  { "id": "e92c7b98", "name": "Munniks", "age": 78 },
  { "id": "e750b2a", "name": "O'Grady", "age": 70 },
  { "id": "18d0cb7a", "name": "Gustavo", "age": 18 },
  { "id": "42af710d", "name": "Varden", "age": 43 },
  { "id": "3eb706fc", "name": "Novak", "age": 34 },
  { "id": "58571aa4", "name": "Sateia", "age": 56 },
  { "id": "23587cd2", "name": "Evans", "age": 58 },
  { "id": "e571d9a0", "name": "Natala", "age": 50 },
  { "id": "111cfdc1", "name": "Giarla", "age": 27 },
  { "id": "40cf4898", "name": "Marchak", "age": 66 },
  { "id": "c4abac8f", "name": "Cyma", "age": 83 },
  { "id": "e01654bf", "name": "Krongold", "age": 27 },
  { "id": "e0d61e79", "name": "Castle", "age": 55 },
  { "id": "786b7cb0", "name": "Eade", "age": 28 },
  { "id": "58db84b4", "name": "Joya", "age": 60 },
  { "id": "ca587926", "name": "Anders", "age": 20 },
  { "id": "4348ac57", "name": "Latton", "age": 29 },
  { "id": "ea001317", "name": "Mountford", "age": 27 },
  { "id": "fa8fbfd8", "name": "Bonnee", "age": 76 },
  { "id": "51b01b8e", "name": "Aletha", "age": 62 },
  { "id": "bfb502dc", "name": "Norita", "age": 20 },
  { "id": "d2ade9a1", "name": "Pippy", "age": 83 },
  { "id": "74b520fd", "name": "Sindee", "age": 63 },
  { "id": "c889c11c", "name": "Serafine", "age": 44 },
  { "id": "30fa45f4", "name": "Conchita", "age": 62 },
  { "id": "d1cef01d", "name": "Maryann", "age": 65 },
  { "id": "bcdec114", "name": "Ramses", "age": 54 },
  { "id": "c6de3b68", "name": "Huxham", "age": 74 },
  { "id": "aaac8b6a", "name": "MacLay", "age": 58 },
  { "id": "2b8d51ce", "name": "Fen", "age": 52 },
  { "id": "6466e7f9", "name": "Orit", "age": 23 },
  { "id": "3a8b5e7f", "name": "Mur", "age": 29 },
  { "id": "39bda924", "name": "Tabbitha", "age": 22 },
  { "id": "72ec1375", "name": "Erlandson", "age": 67 },
  { "id": "f0bda18b", "name": "Raskind", "age": 45 },
  { "id": "d9136fe3", "name": "Rosane", "age": 25 },
  { "id": "b40fc2e7", "name": "Neddy", "age": 71 },
  { "id": "229d9f8", "name": "Halbeib", "age": 54 },
  { "id": "d1cbd9f", "name": "Maurise", "age": 55 },
  { "id": "d30cc197", "name": "Helprin", "age": 33 },
  { "id": "e2de8401", "name": "Brigham", "age": 67 },
  { "id": "ec17d1f7", "name": "Bickart", "age": 51 },
  { "id": "bbb2bb3d", "name": "Bunns", "age": 59 },
  { "id": "efca2f8c", "name": "Cleve", "age": 84 },
  { "id": "e427a588", "name": "Jaclin", "age": 54 },
  { "id": "a643e8da", "name": "Octavus", "age": 34 },
  { "id": "a4148375", "name": "Otti", "age": 63 },
  { "id": "159f5a2e", "name": "Mariellen", "age": 82 },
  { "id": "c6faf65f", "name": "Stclair", "age": 85 },
  { "id": "70e04fe7", "name": "Matthei", "age": 17 },
  { "id": "fe3c5ea4", "name": "Elberfeld", "age": 48 },
  { "id": "bf099434", "name": "Voletta", "age": 36 },
  { "id": "9ecf59fb", "name": "Chick", "age": 61 },
  { "id": "c7b20bef", "name": "Monarski", "age": 63 },
  { "id": "65b0cf54", "name": "Kenon", "age": 44 },
  { "id": "ac5ca7bc", "name": "Julide", "age": 80 },
  { "id": "ef8fed05", "name": "Susan", "age": 45 },
  { "id": "7e80ac49", "name": "Laius", "age": 25 },
  { "id": "c92243f", "name": "Sandeep", "age": 23 },
  { "id": "791eb177", "name": "Wilhelm", "age": 23 },
  { "id": "f67ff50c", "name": "Derek", "age": 66 },
  { "id": "20d72707", "name": "Sapphira", "age": 39 },
  { "id": "df980ca8", "name": "Eph", "age": 66 },
  { "id": "5992906e", "name": "McRipley", "age": 40 },
  { "id": "476e50bc", "name": "Irene", "age": 80 },
  { "id": "2040c30c", "name": "Carny", "age": 44 },
  { "id": "89722b5", "name": "Backer", "age": 55 },
  { "id": "7e5ac98b", "name": "Arabelle", "age": 47 },
  { "id": "df04fe09", "name": "Dulcie", "age": 61 },
  { "id": "7c48f8ad", "name": "Orel", "age": 63 },
  { "id": "26d101d5", "name": "Giverin", "age": 17 },
  { "id": "f5a46a90", "name": "Gamages", "age": 30 },
  { "id": "a208e4c8", "name": "Cherri", "age": 74 },
  { "id": "11d7639a", "name": "Scarito", "age": 26 },
  { "id": "f54b0eac", "name": "Forster", "age": 72 },
  { "id": "4a62b483", "name": "Petronella", "age": 59 },
  { "id": "fc6fc95", "name": "Dede", "age": 65 },
  { "id": "3df2af08", "name": "Holt", "age": 72 },
  { "id": "62a75be7", "name": "Chariot", "age": 63 },
  { "id": "b65678c2", "name": "Sawyer", "age": 78 },
  { "id": "6f9e7615", "name": "Lally", "age": 19 },
  { "id": "cdc61f79", "name": "Grenville", "age": 71 },
  { "id": "79cda48f", "name": "Keely", "age": 79 },
  { "id": "73d90161", "name": "Lora", "age": 71 },
  { "id": "1f8db684", "name": "Shem", "age": 62 },
  { "id": "4cfb939b", "name": "Barcus", "age": 35 },
  { "id": "8af3600f", "name": "Sybila", "age": 73 },
  { "id": "8108a545", "name": "Bartlett", "age": 57 },
  { "id": "dafdfad5", "name": "Saideman", "age": 35 },
  { "id": "616c9dd6", "name": "Cony", "age": 72 },
  { "id": "d0948d61", "name": "Tobi", "age": 75 },
  { "id": "c4bcc426", "name": "Stovall", "age": 24 },
  { "id": "b12b8aa2", "name": "Sirmons", "age": 76 },
  { "id": "4be4157", "name": "Madai", "age": 47 },
  { "id": "98ba36c7", "name": "Peoples", "age": 17 },
  { "id": "975f88fb", "name": "Nich", "age": 39 },
  { "id": "c037a3a", "name": "Swisher", "age": 76 },
  { "id": "af00afd", "name": "Africah", "age": 29 },
  { "id": "91a18111", "name": "Dory", "age": 43 },
  { "id": "af1d65cb", "name": "Middlesworth", "age": 79 },
  { "id": "60e47df0", "name": "On", "age": 20 },
  { "id": "eb25012c", "name": "Gilly", "age": 58 },
  { "id": "7ef098e5", "name": "Avi", "age": 73 },
  { "id": "37bbec2f", "name": "Lukas", "age": 71 },
  { "id": "acd4a055", "name": "Kilbride", "age": 35 },
  { "id": "6711183f", "name": "Pearline", "age": 53 },
  { "id": "f9f4ee02", "name": "Hibbitts", "age": 34 },
  { "id": "9c7ead52", "name": "Bleier", "age": 78 },
  { "id": "c1d3d4e1", "name": "Chance", "age": 17 },
  { "id": "9e21abee", "name": "Wallache", "age": 56 },
  { "id": "e2f9e36", "name": "Hubey", "age": 54 },
  { "id": "8141f2d7", "name": "Felty", "age": 37 },
  { "id": "c5d92b47", "name": "Eaves", "age": 29 },
  { "id": "a1ce4d6e", "name": "Marlyn", "age": 20 },
  { "id": "8f3679fe", "name": "Geffner", "age": 18 },
  { "id": "49c6cc4", "name": "Pennie", "age": 50 },
  { "id": "1fb3de7c", "name": "Madel", "age": 52 },
  { "id": "d8ebeec6", "name": "Reube", "age": 18 },
  { "id": "73f4cbcb", "name": "Brigette", "age": 31 },
  { "id": "945b83f3", "name": "Selig", "age": 49 },
  { "id": "fc682ed1", "name": "Thacker", "age": 57 },
  { "id": "60e286a7", "name": "Ally", "age": 49 },
  { "id": "9283ac4b", "name": "Darsie", "age": 25 },
  { "id": "6eb0cb2c", "name": "Belshin", "age": 74 },
  { "id": "8e18e52d", "name": "Gehman", "age": 61 },
  { "id": "90505e76", "name": "Gifferd", "age": 72 },
  { "id": "a527c006", "name": "Rosmarin", "age": 18 },
  { "id": "e26adc9e", "name": "Sturges", "age": 36 },
  { "id": "e02c09d6", "name": "Yael", "age": 32 },
  { "id": "7c55971e", "name": "Josias", "age": 76 },
  { "id": "17c26a8a", "name": "Naam", "age": 72 },
  { "id": "352c0184", "name": "Flyn", "age": 76 },
  { "id": "301484f8", "name": "Hyacinthe", "age": 54 },
  { "id": "fe3c5ea4", "name": "Elberfeld", "age": 48 },
  { "id": "b3b3bd06", "name": "Curran", "age": 34 },
  { "id": "ed61cb0", "name": "Egon", "age": 18 },
  { "id": "830afa1e", "name": "Weasner", "age": 42 },
  { "id": "2ab1a1c9", "name": "Sev", "age": 67 },
  { "id": "cf1e7f48", "name": "Berkeley", "age": 72 },
  { "id": "f3127ba3", "name": "Johnsson", "age": 33 },
  { "id": "a8537166", "name": "Trygve", "age": 22 },
  { "id": "e32ddc61", "name": "Pawsner", "age": 85 },
  { "id": "6702bbba", "name": "Beesley", "age": 84 },
  { "id": "2ec8b858", "name": "Fiore", "age": 54 },
  { "id": "133a90ea", "name": "Furtek", "age": 16 },
  { "id": "d8ebeec6", "name": "Reube", "age": 18 },
  { "id": "4214f286", "name": "Naara", "age": 48 },
  { "id": "87edb1b0", "name": "Qulllon", "age": 46 },
  { "id": "db4398ed", "name": "Kosel", "age": 31 },
  { "id": "e65ef836", "name": "Noman", "age": 52 },
  { "id": "e4d49dd5", "name": "Margaretta", "age": 81 },
  { "id": "5440ac36", "name": "Dyl", "age": 60 },
  { "id": "e2057dca", "name": "Tatman", "age": 44 },
  { "id": "ff2428e8", "name": "Andromede", "age": 84 },
  { "id": "248596ab", "name": "Rothschild", "age": 81 },
  { "id": "b99f6e7a", "name": "Jyoti", "age": 52 },
  { "id": "dd6a35b3", "name": "Picardi", "age": 35 },
  { "id": "e6eb0b84", "name": "Anthea", "age": 24 },
  { "id": "7f3f2b8b", "name": "Faun", "age": 83 },
  { "id": "17bb2091", "name": "Berlin", "age": 63 },
  { "id": "3668b3b0", "name": "Royal", "age": 64 },
  { "id": "35cf8bdc", "name": "Erinna", "age": 20 },
  { "id": "1de7d0f7", "name": "Spears", "age": 81 },
  { "id": "6dfd47b6", "name": "Donelu", "age": 26 },
  { "id": "9ad20321", "name": "Lytle", "age": 61 },
  { "id": "e9a63128", "name": "Tuppeny", "age": 54 },
  { "id": "51c58772", "name": "Rubinstein", "age": 18 },
  { "id": "c725e301", "name": "Susi", "age": 85 },
  { "id": "e129002", "name": "Lurline", "age": 84 }
]
